setup.py
taskutils.py
taskutils.egg-info/PKG-INFO
taskutils.egg-info/SOURCES.txt
taskutils.egg-info/dependency_links.txt
taskutils.egg-info/top_level.txt