Metadata-Version: 1.0
Name: taskutils
Version: 0.1
Summary: A multithreaded task scheduler for task queues and recurrent tasks
Home-page: https://github.com/mdipierro/taskutils
Author: Massimo DiPierro
Author-email: massimo.dipierro@gmail.com
License: BSD
Keywords: task scheduler
Platform: UNKNOWN
